pk1/__init__.py
pk1/manage.py
pk1/server.py
pk1/clouds/__init__.py
pk1/clouds/admin.py
pk1/clouds/apps.py
pk1/clouds/models.py
pk1/clouds/pagination.py
pk1/clouds/permissions.py
pk1/clouds/serializers.py
pk1/clouds/signals.py
pk1/clouds/tests.py
pk1/clouds/urls.py
pk1/clouds/utils.py
pk1/clouds/views.py
pk1/clouds/base/__init__.py
pk1/clouds/base/admin.py
pk1/clouds/base/models.py
pk1/clouds/drivers/__init__.py
pk1/clouds/drivers/cstcloud.py
pk1/clouds/drivers/evcloud.py
pk1/clouds/drivers/h3cloudos.py
pk1/clouds/drivers/openstack.py
pk1/clouds/management/__init__.py
pk1/clouds/management/commands/__init__.py
pk1/clouds/management/commands/monitor-cloud.py
pk1/conf/__init__.py
pk1/conf/settings.py
pk1/conf/urls.py
pk1/conf/uwsgi.ini
pk1/conf/wsgi.py
pk1/data/__init__.py
pk1/data/admin.py
pk1/data/apps.py
pk1/data/models.py
pk1/data/serializers.py
pk1/data/signals.py
pk1/data/tests.py
pk1/data/urls.py
pk1/data/views.py
pk1/data/management/__init__.py
pk1/data/management/commands/__init__.py
pk1/data/management/commands/monitor-data.py
pk1/engines/__init__.py
pk1/engines/admin.py
pk1/engines/apps.py
pk1/engines/models.py
pk1/engines/serializers.py
pk1/engines/signals.py
pk1/engines/tests.py
pk1/engines/urls.py
pk1/engines/utils.py
pk1/engines/views.py
pk1/engines/drivers/__init__.py
pk1/engines/drivers/ambari.py
pk1/engines/management/__init__.py
pk1/engines/management/commands/__init__.py
pk1/engines/management/commands/monitor-engine.py
pk1/scispace/__init__.py
pk1/scispace/tests.py
pk1/scispace/urls.py
pk1/scispace/utils.py
pk1/scispace/templates/accounts_login.html
pk1/scispace/templates/cluster_add.html
pk1/scispace/templates/cluster_info.html
pk1/scispace/templates/cluster_instance_list.html
pk1/scispace/templates/cluster_list.html
pk1/scispace/templates/data_instance_add.html
pk1/scispace/templates/data_instance_delete.html
pk1/scispace/templates/data_instance_list.html
pk1/scispace/templates/data_instance_operation_info.html
pk1-0.3.3.dist-info/LICENSE
pk1-0.3.3.dist-info/METADATA
pk1-0.3.3.dist-info/WHEEL
pk1-0.3.3.dist-info/entry_points.txt
pk1-0.3.3.dist-info/top_level.txt
pk1-0.3.3.dist-info/RECORD
