Metadata-Version: 2.1
Name: pk1
Version: 0.3.3
Summary: PackOne: Pack clouds, engines and data services into one light stack.
Home-page: https://github.com/cas-bigdatalab/packone
Author: Excel Wang
Author-email: wanghj@cnic.com
License: Apache-2.0 Licence
Keywords: pip,packone
Platform: UNKNOWN
Classifier: Programming Language :: Python :: 3
Classifier: Operating System :: OS Independent
License-File: LICENSE
Requires-Dist: httplib2 (==0.18.1)
Requires-Dist: django-jet-opt (==1.0.8)
Requires-Dist: django (==2.2.28)
Requires-Dist: uwsgi (==2.0.21)
Requires-Dist: ambari (==0.1.7)
Requires-Dist: django-admin-auto (==0.1.1)
Requires-Dist: djangorestframework (==3.10.3)
Requires-Dist: djangorestframework-simplejwt (==4.3.0)
Requires-Dist: django-simpleui (==4.0.3)
Requires-Dist: django-filter (==2.4.0)
Requires-Dist: psycopg2-binary (==2.8.6)
Requires-Dist: coreapi (==2.3.3)
Requires-Dist: paramiko (==2.7.2)
Requires-Dist: scp (==0.14.4)
Requires-Dist: django-cors-headers (==2.4.0)
Requires-Dist: python-novaclient (==17.7.0)
Requires-Dist: python-cinderclient (==7.4.1)
Requires-Dist: python-glanceclient (==3.6.0)
Requires-Dist: django-autocomplete-light (==3.8.2)
